NWS_Weather/__init__.py
NWS_Weather/alert.py
NWS_Weather/current_weather.py
NWS_Weather/forcast.py
NWS_Weather/get_alerts.py
NWS_Weather/observation.py
NWS_Weather/predicted_weather.py
NWS_Weather-1.1.1.dist-info/LICENSE
NWS_Weather-1.1.1.dist-info/METADATA
NWS_Weather-1.1.1.dist-info/WHEEL
NWS_Weather-1.1.1.dist-info/top_level.txt
NWS_Weather-1.1.1.dist-info/RECORD
