Metadata-Version: 2.1
Name: NWS-Weather
Version: 1.1.1
Summary: A package for retrieving weather data from the National Weather Service
Home-page: https://github.com/Pizzarules668/NWS-Weather
Author: Colin Sutter
Author-email: contact@csutter.dev
License-File: LICENSE
Requires-Dist: requests
Requires-Dist: geopy
Requires-Dist: datetime
